ftest/__init__.py
ftest/tcase.py
ftest/treport.py
pyFtest-1.7.dist-info/DESCRIPTION.rst
pyFtest-1.7.dist-info/METADATA
pyFtest-1.7.dist-info/RECORD
pyFtest-1.7.dist-info/WHEEL
pyFtest-1.7.dist-info/metadata.json
pyFtest-1.7.dist-info/top_level.txt
tests/__init__.py
tests/ftest_test.py
tests/test.py
