Metadata-Version: 2.0
Name: pyFtest
Version: 1.7
Summary: A pure Python library designed to auto-test for FREESWITCH easy 
Home-page: https://github.com/sudaning/Ftest
Author: Daning Su
Author-email: sudaning@sina.com
License: LICENSE
Platform: linux
Classifier: Development Status :: 5 - Production/Stable
Classifier: Intended Audience :: Science/Research
Classifier: Natural Language :: Chinese (Simplified)
Classifier: Topic :: Text Processing
Classifier: Operating System :: POSIX :: Linux
Classifier: License :: OSI Approved :: MIT License
Classifier: Programming Language :: Python :: 2
Classifier: Programming Language :: Python :: 2.7
Requires-Dist: pyFneko (>=3.4)
Requires-Dist: pyyaml (>=3.12)
Requires-Dist: xlwt (>=1.2.0)
